pycodes/__init__.py
pycodes/ean.py
pycodes/exceptions.py
pycodes-0.0.1.dist-info/DESCRIPTION.rst
pycodes-0.0.1.dist-info/METADATA
pycodes-0.0.1.dist-info/RECORD
pycodes-0.0.1.dist-info/WHEEL
pycodes-0.0.1.dist-info/metadata.json
pycodes-0.0.1.dist-info/top_level.txt
