Metadata-Version: 2.0
Name: pycodes
Version: 0.0.1
Summary: A library with utils to validate product codes
Home-page: http://github.com/blazaid/pycodes/
Author: blazaid
Author-email: alberto.da@gmail.com
License: Apache License 2.0
Platform: any
Classifier: Development Status :: 1 - Planning
Classifier: Intended Audience :: Developers
Classifier: License :: OSI Approved :: Apache Software License
Classifier: Natural Language :: English
Classifier: Operating System :: OS Independent
Classifier: Programming Language :: Python :: 3.6
Classifier: Topic :: Utilities
